{
    "191043": {
        "FD": {
            "nonfd": "2",
            "law": "1",
            "chaos": "2"
        },
        "Element": "3",
        "Type": {
            "nonfd": "TypeATK",
            "law": "TypeDEF",
            "chaos": "TypeWEA"
        },
        "Base_Stat": {
            "hp": 22456,
            "atk": 741,
            "def": 553,
            "spd": 591
        },
        "LB": [
            [900	,15	,15	,15],
            [1800	,30	,30	,30],
            [2925	,48	,48	,48],
            [4500	,75	,75	,75]
        ],
        "DB": [
            [500,	9,	9,	9],
            [640,	10,	10,	10],
            [800,	11,	11,	11],
            [980,	12,	12,	12],
            [1190,	14,	14,	14],
            [1430,	17,	17,	17],
            [1700,	20,	20,	20],
            [1990,	24,	24,	24],
            [2300,	28,	28,	28]
        ]
    }

}
